bloboluni/__init__.py
bloboluni/serializers.py
bloboluni/storage.py
bloboluni-2.0.1.dist-info/METADATA
bloboluni-2.0.1.dist-info/WHEEL
bloboluni-2.0.1.dist-info/licenses/LICENSE
bloboluni-2.0.1.dist-info/RECORD
