Metadata-Version: 2.1
Name: bloboluni
Version: 2.0.1
Summary: A simple package for storing and retrieving blobs of data from Azure Blob Storage
Project-URL: Homepage, https://github.com/MartinMoan/blobstorage
Project-URL: Bug Tracker, https://github.com/MartinMoan/blobstorage/issues
Author-email: Martin Moan <martin.moan1@gmail.com>
License: Copyright (c) 2023 Martin Hoff Moan
License-File: LICENSE
Classifier: License :: OSI Approved :: MIT License
Classifier: Operating System :: OS Independent
Classifier: Programming Language :: Python :: 3
Requires-Python: >=3.10
Requires-Dist: azure-identity>=1
Requires-Dist: azure-storage-blob>=1
Requires-Dist: jsonpickle>=3
Requires-Dist: python-dotenv>=1
Requires-Dist: requests>2
